specker/__init__.py
specker/content.py
specker/loader.py
specker/specs/specker.spec
specker-1.5.2.dist-info/LICENSE.md
specker-1.5.2.dist-info/METADATA
specker-1.5.2.dist-info/WHEEL
specker-1.5.2.dist-info/entry_points.txt
specker-1.5.2.dist-info/top_level.txt
specker-1.5.2.dist-info/RECORD
