Metadata-Version: 2.1
Name: specker
Version: 1.5.2
Summary: Specker JSON Specification Validator
Author-email: AccidentallyTheCable <cableninja@cableninja.net>
License: GPLv3
Project-URL: Homepage, https://gitlab.com/accidentallythecable-public/python-modules/python-specker/
Project-URL: Bug Tracker, https://gitlab.com/accidentallythecable-public/python-modules/python-specker/issues
Classifier: Programming Language :: Python :: 3
Classifier: License :: OSI Approved :: GNU General Public License v3 (GPLv3)
Classifier: Operating System :: OS Independent
Classifier: Environment :: Console
Classifier: Topic :: Software Development :: Documentation
Classifier: Topic :: Text Processing
Requires-Python: >=3.9
License-File: LICENSE.md
